palgo/__init__.py
palgo-0.0.1.dist-info/LICENSE
palgo-0.0.1.dist-info/METADATA
palgo-0.0.1.dist-info/WHEEL
palgo-0.0.1.dist-info/top_level.txt
palgo-0.0.1.dist-info/RECORD
